jsfiddle_readme_generator/__init__.py
jsfiddle_readme_generator/__main__.py
markdown_table/__init__.py
markdown_table-2019.4.13.dist-info/METADATA
markdown_table-2019.4.13.dist-info/WHEEL
markdown_table-2019.4.13.dist-info/top_level.txt
markdown_table-2019.4.13.dist-info/RECORD
