Metadata-Version: 2.1
Name: markdown-table
Version: 2019.4.13
Summary: markown table generator
Home-page: https://github.com/looking-for-a-job/markdown-table.py
License: UNKNOWN
Keywords: markown table
Platform: UNKNOWN
Classifier: Operating System :: OS Independent
Classifier: Programming Language :: Python
Classifier: Programming Language :: Python :: 2
Classifier: Programming Language :: Python :: 2.7
Classifier: Programming Language :: Python :: 3
Classifier: Programming Language :: Python :: 3.4
Classifier: Programming Language :: Python :: 3.5
Classifier: Programming Language :: Python :: 3.6
Classifier: Programming Language :: Python :: 3.7
